arenz_group_python/__init__.py
arenz_group_python/data_treatment/__init__.py
arenz_group_python/data_treatment/autoclave_synthesis.py
arenz_group_python/data_treatment/cv_data.py_BK
arenz_group_python/data_treatment/cv_datas.py_BK
arenz_group_python/data_treatment/ec_data.py_BK
arenz_group_python/data_treatment/ec_datas.py_BK
arenz_group_python/data_treatment/ec_setup.py_BK
arenz_group_python/data_treatment/util.py
arenz_group_python/data_treatment/util_graph.py
arenz_group_python/elabftw/__init__.py
arenz_group_python/elabftw/elabftw.py
arenz_group_python/file/__init__.py
arenz_group_python/file/file_dict.py
arenz_group_python/file/key_values_to_file.py
arenz_group_python/file/rw_dict_
arenz_group_python/project/__init__.py
arenz_group_python/project/default_paths.py
arenz_group_python/project/make_file_eLabFTW.py
arenz_group_python/project/make_files.py
arenz_group_python/project/util_paths.py
arenz_group_python-0.4.4.dist-info/METADATA
arenz_group_python-0.4.4.dist-info/WHEEL
arenz_group_python-0.4.4.dist-info/licenses/LICENSE
arenz_group_python-0.4.4.dist-info/RECORD
