Metadata-Version: 2.4
Name: Arenz_Group_Python
Version: 0.4.4
Summary: a pip-installable package with function for Arenz Group
Project-URL: Homepage, https://github.com/NanoElectroCatalysis/Arenz_Group_Python
Project-URL: Documentation, https://nanoelectrocatalysis.github.io/Arenz_Group_Python
Project-URL: Repository, https://github.com/NanoElectroCatalysis/Arenz_Group_Python
Project-URL: Issues, https://github.com/NanoElectroCatalysis/Arenz_Group_Python
Project-URL: Changelog, https://github.com/NanoElectroCatalysis/Arenz_Group_Python
Author-email: Gustav Wiberg <gustav.wiberg@unibe.ch>
Maintainer-email: Gustav Wiberg <gustav.wiberg@unibe.ch>
License: MIT License
License-File: LICENSE
Keywords: arenz group,python,tdms
Classifier: Development Status :: 4 - Beta
Classifier: Operating System :: OS Independent
Classifier: Programming Language :: Python
Requires-Python: >=3.11
Requires-Dist: ec4py
Requires-Dist: elabapi-python
Requires-Dist: matplotlib
Requires-Dist: nptdms
Requires-Dist: numpy
Requires-Dist: pandas
Requires-Dist: pathlib
Requires-Dist: scipy
